README.md
setup.py
vahfka/__init__.py
vahfka/vahfka.py
vahfka.egg-info/PKG-INFO
vahfka.egg-info/SOURCES.txt
vahfka.egg-info/dependency_links.txt
vahfka.egg-info/requires.txt
vahfka.egg-info/top_level.txt