Metadata-Version: 2.1
Name: vahfka
Version: 2.0.0
Summary: Kafka-Vahfka
Home-page: UNKNOWN
License: UNKNOWN
Platform: UNKNOWN
